nonebot_plugin_tts_gal/__init__.py
nonebot_plugin_tts_gal/attentions.py
nonebot_plugin_tts_gal/cc_cedict_local.py
nonebot_plugin_tts_gal/commons.py
nonebot_plugin_tts_gal/config.py
nonebot_plugin_tts_gal/depends.py
nonebot_plugin_tts_gal/function.py
nonebot_plugin_tts_gal/initial.py
nonebot_plugin_tts_gal/kmandarin_8105_local.py
nonebot_plugin_tts_gal/mel_processing.py
nonebot_plugin_tts_gal/models.py
nonebot_plugin_tts_gal/modules.py
nonebot_plugin_tts_gal/monotonic_align/__init__.py
nonebot_plugin_tts_gal/monotonic_align/core.py
nonebot_plugin_tts_gal/text/__init__.py
nonebot_plugin_tts_gal/text/cleaners.py
nonebot_plugin_tts_gal/text/LICENSE
nonebot_plugin_tts_gal/text/symbols.py
nonebot_plugin_tts_gal/transforms.py
nonebot_plugin_tts_gal/utils.py
nonebot_plugin_tts_gal-0.3.11.dist-info/LICENSE
nonebot_plugin_tts_gal-0.3.11.dist-info/WHEEL
nonebot_plugin_tts_gal-0.3.11.dist-info/METADATA
nonebot_plugin_tts_gal-0.3.11.dist-info/RECORD
