Metadata-Version: 2.1
Name: nonebot-plugin-tts-gal
Version: 0.3.11
Summary: 基于nonebot2和vits的本地化角色语音合成插件
Home-page: https://github.com/dpm12345/nonebot_plugin_tts_gal
License: MIT
Author: dpm12345
Author-email: 1006975692@qq.com
Requires-Python: >=3.8,<4.0
Classifier: License :: OSI Approved :: MIT License
Classifier: Programming Language :: Python :: 3
Classifier: Programming Language :: Python :: 3.8
Classifier: Programming Language :: Python :: 3.9
Classifier: Programming Language :: Python :: 3.10
Requires-Dist: ffmpy (>=0.3.0,<0.4.0)
Requires-Dist: httpx (>=0.23.1,<0.24.0)
Requires-Dist: janome (>=0.4.2,<0.5.0)
Requires-Dist: jieba (>=0.42.1,<0.43.0)
Requires-Dist: nonebot-adapter-onebot (>=2.1.1,<3.0.0)
Requires-Dist: nonebot-plugin-apscheduler (>=0.2.0,<0.3.0)
Requires-Dist: nonebot2 (>=2.0.0b4,<3.0.0)
Requires-Dist: numba (>=0.56.2,<0.57.0)
Requires-Dist: numpy (>=1.20.0,<2.0.0)
Requires-Dist: pyopenjtalk (>=0.3.0,<0.4.0)
Requires-Dist: pypinyin (>=0.47.0,<0.48.0)
Requires-Dist: scipy (>=1.5.2,<2.0.0)
Requires-Dist: torch (>=1.6.0,<2.0.0)
Requires-Dist: unidecode (>=1.1.1,<2.0.0)
Project-URL: Repository, https://github.com/dpm12345/nonebot_plugin_tts_gal
